anyblok_pyramid_rest_api/__init__.py
anyblok_pyramid_rest_api/adapter.py
anyblok_pyramid_rest_api/crud_resource.py
anyblok_pyramid_rest_api/pyramid_config.py
anyblok_pyramid_rest_api/querystring.py
anyblok_pyramid_rest_api/schema.py
anyblok_pyramid_rest_api/validator.py
anyblok_pyramid_rest_api/test_bloks/__init__.py
anyblok_pyramid_rest_api/test_bloks/test_1/__init__.py
anyblok_pyramid_rest_api/test_bloks/test_1/model.py
anyblok_pyramid_rest_api/test_bloks/test_1/schema.py
anyblok_pyramid_rest_api/test_bloks/test_1/views.py
anyblok_pyramid_rest_api/test_bloks/test_10/__init__.py
anyblok_pyramid_rest_api/test_bloks/test_10/model.py
anyblok_pyramid_rest_api/test_bloks/test_10/schema.py
anyblok_pyramid_rest_api/test_bloks/test_10/views.py
anyblok_pyramid_rest_api/test_bloks/test_2/__init__.py
anyblok_pyramid_rest_api/test_bloks/test_2/views.py
anyblok_pyramid_rest_api/test_bloks/test_3/__init__.py
anyblok_pyramid_rest_api/test_bloks/test_3/model.py
anyblok_pyramid_rest_api/test_bloks/test_3/schema.py
anyblok_pyramid_rest_api/test_bloks/test_3/views.py
anyblok_pyramid_rest_api/test_bloks/test_4/__init__.py
anyblok_pyramid_rest_api/test_bloks/test_4/model.py
anyblok_pyramid_rest_api/test_bloks/test_4/schema.py
anyblok_pyramid_rest_api/test_bloks/test_4/views.py
anyblok_pyramid_rest_api/test_bloks/test_5/__init__.py
anyblok_pyramid_rest_api/test_bloks/test_5/model.py
anyblok_pyramid_rest_api/test_bloks/test_5/schema.py
anyblok_pyramid_rest_api/test_bloks/test_5/views.py
anyblok_pyramid_rest_api/test_bloks/test_6/__init__.py
anyblok_pyramid_rest_api/test_bloks/test_6/model.py
anyblok_pyramid_rest_api/test_bloks/test_6/schema.py
anyblok_pyramid_rest_api/test_bloks/test_6/views.py
anyblok_pyramid_rest_api/test_bloks/test_7/__init__.py
anyblok_pyramid_rest_api/test_bloks/test_7/model.py
anyblok_pyramid_rest_api/test_bloks/test_7/schema.py
anyblok_pyramid_rest_api/test_bloks/test_7/views.py
anyblok_pyramid_rest_api/test_bloks/test_8/__init__.py
anyblok_pyramid_rest_api-0.7.0.dist-info/LICENSE
anyblok_pyramid_rest_api-0.7.0.dist-info/METADATA
anyblok_pyramid_rest_api-0.7.0.dist-info/WHEEL
anyblok_pyramid_rest_api-0.7.0.dist-info/entry_points.txt
anyblok_pyramid_rest_api-0.7.0.dist-info/top_level.txt
anyblok_pyramid_rest_api-0.7.0.dist-info/RECORD
