Metadata-Version: 2.1
Name: anyblok-pyramid-rest-api
Version: 0.7.0
Summary: Tools to build rest api's
Home-page: https://github.com/AnyBlok/anyblok-pyramid-rest-api
Author: Franck Bret
Author-email: franckbret@gmail.com
License: UNKNOWN
Keywords: anyblok-pyramid-rest-api
Platform: UNKNOWN
Classifier: Development Status :: 2 - Pre-Alpha
Classifier: Intended Audience :: Developers
Classifier: Natural Language :: English
Classifier: Programming Language :: Python :: 3
Classifier: Programming Language :: Python :: 3.5
Classifier: Programming Language :: Python :: 3.6
Classifier: Programming Language :: Python :: 3.7
Classifier: Programming Language :: Python :: 3.8
Classifier: Programming Language :: Python :: 3.9
Classifier: Topic :: Software Development :: Libraries :: Python Modules
Classifier: Framework :: Pyramid
Classifier: Topic :: Internet :: WWW/HTTP
Classifier: Topic :: Internet :: WWW/HTTP :: HTTP Servers
Classifier: Topic :: Internet :: WWW/HTTP :: WSGI :: Server
Classifier: License :: OSI Approved :: Mozilla Public License 2.0 (MPL 2.0)
Requires-Dist: anyblok
Requires-Dist: anyblok-marshmallow
Requires-Dist: anyblok-pyramid
Requires-Dist: cornice
